handyjupyter/__init__.py
handyjupyter/visual/__init__.py
handyjupyter/visual/visual.py
handyjupyter-0.0.1.dist-info/METADATA
handyjupyter-0.0.1.dist-info/WHEEL
handyjupyter-0.0.1.dist-info/top_level.txt
handyjupyter-0.0.1.dist-info/RECORD
