Metadata-Version: 2.1
Name: handyjupyter
Version: 0.0.1
Summary: Just for convenience when using jupyter
Home-page: https://github.com/AronWater/handyjupyter
Author: AronWater
Author-email: kclukac@connect.ust.hk
License: UNKNOWN
Platform: UNKNOWN
Classifier: Programming Language :: Python :: 3
Classifier: License :: OSI Approved :: MIT License
Classifier: Operating System :: OS Independent
Requires-Python: >=3.6
